duetector/__init__.py
duetector/config.py
duetector/db.py
duetector/exceptions.py
duetector/log.py
duetector/otel.py
duetector/utils.py
duetector/analyzer/__init__.py
duetector/analyzer/base.py
duetector/analyzer/db.py
duetector/analyzer/models.py
duetector/analyzer/register.py
duetector/analyzer/jaeger/__init__.py
duetector/analyzer/jaeger/analyzer.py
duetector/analyzer/jaeger/proto/__init__.py
duetector/analyzer/jaeger/proto/model_pb2.py
duetector/analyzer/jaeger/proto/model_pb2.pyi
duetector/analyzer/jaeger/proto/query_pb2.py
duetector/analyzer/jaeger/proto/query_pb2.pyi
duetector/analyzer/jaeger/proto/query_pb2_grpc.py
duetector/analyzer/jaeger/proto/gogoproto/gogo_pb2.py
duetector/analyzer/jaeger/proto/google/api/annotations_pb2.py
duetector/analyzer/jaeger/proto/google/api/http_pb2.py
duetector/cli/__init__.py
duetector/cli/daemon.py
duetector/cli/main.py
duetector/cli/server.py
duetector/cli/server_daemon.py
duetector/collectors/__init__.py
duetector/collectors/base.py
duetector/collectors/db.py
duetector/collectors/models.py
duetector/collectors/otel.py
duetector/collectors/register.py
duetector/extension/__init__.py
duetector/extension/analyzer/__init__.py
duetector/extension/collector/__init__.py
duetector/extension/filter/__init__.py
duetector/extension/injector/__init__.py
duetector/extension/tracer/__init__.py
duetector/filters/__init__.py
duetector/filters/base.py
duetector/filters/pattern.py
duetector/filters/register.py
duetector/injectors/__init__.py
duetector/injectors/base.py
duetector/injectors/docker.py
duetector/injectors/inspector.py
duetector/injectors/k8s.py
duetector/injectors/register.py
duetector/managers/__init__.py
duetector/managers/analyzer.py
duetector/managers/base.py
duetector/managers/collector.py
duetector/managers/filter.py
duetector/managers/injector.py
duetector/managers/tracer.py
duetector/monitors/__init__.py
duetector/monitors/base.py
duetector/monitors/bcc_monitor.py
duetector/monitors/sh_monitor.py
duetector-0.1.3.dist-info/METADATA
duetector-0.1.3.dist-info/WHEEL
duetector-0.1.3.dist-info/entry_points.txt
duetector-0.1.3.dist-info/licenses/LICENSE
duetector-0.1.3.dist-info/RECORD
