Metadata-Version: 2.1
Name: duetector
Version: 0.1.3
Summary: duetector
Project-URL: Source, https://github.com/hitsz-ids/duetector
Author: hitsz-ids
License: Apache Software License 2.0
License-File: LICENSE
Keywords: duetector
Classifier: Programming Language :: Python :: 3
Classifier: Programming Language :: Python :: 3.8
Classifier: Programming Language :: Python :: 3.9
Classifier: Programming Language :: Python :: 3.10
Classifier: Programming Language :: Python :: 3.11
Requires-Python: >=3.8
Requires-Dist: anyio
Requires-Dist: apscheduler
Requires-Dist: click
Requires-Dist: docker
Requires-Dist: fastapi
Requires-Dist: grpcio
Requires-Dist: kubernetes
Requires-Dist: loguru
Requires-Dist: opentelemetry-api
Requires-Dist: opentelemetry-exporter-jaeger
Requires-Dist: opentelemetry-exporter-otlp-proto-grpc
Requires-Dist: opentelemetry-exporter-otlp-proto-http
Requires-Dist: opentelemetry-exporter-zipkin-json
Requires-Dist: opentelemetry-exporter-zipkin-proto-http
Requires-Dist: opentelemetry-sdk
Requires-Dist: opentelemetry-semantic-conventions
Requires-Dist: pluggy
Requires-Dist: protobuf
Requires-Dist: psutil
Requires-Dist: pydantic>=2
Requires-Dist: sqlalchemy>=2
Requires-Dist: tomli
Requires-Dist: tomli-w
Requires-Dist: typing-extensions
Requires-Dist: uvicorn[standard]
Requires-Dist: watchfiles
Provides-Extra: docs
Requires-Dist: autodoc-pydantic; extra == 'docs'
Requires-Dist: sphinx-click; extra == 'docs'
Requires-Dist: sphinx-rtd-theme; extra == 'docs'
Requires-Dist: sphinx<=7.2.4; extra == 'docs'
Provides-Extra: test
Requires-Dist: docker; extra == 'test'
Requires-Dist: httpx; extra == 'test'
Requires-Dist: pytest; extra == 'test'
Requires-Dist: pytest-asyncio; extra == 'test'
Requires-Dist: pytest-cov; extra == 'test'
Requires-Dist: pytest-timeout; extra == 'test'
